aggregates/__init__.py
aggregates/base.py
aggregates/functions.py
aggregates/templates.py
aggregates/conditionals/__init__.py
aggregates/conditionals/base.py
aggregates/conditionals/functions.py
aggregates/conditionals/templates.py
aggregates/strings/__init__.py
aggregates/strings/base.py
aggregates/strings/functions.py
aggregates/strings/templates.py
django_aggregates-0.1.3.dist-info/DESCRIPTION.rst
django_aggregates-0.1.3.dist-info/METADATA
django_aggregates-0.1.3.dist-info/RECORD
django_aggregates-0.1.3.dist-info/WHEEL
django_aggregates-0.1.3.dist-info/metadata.json
django_aggregates-0.1.3.dist-info/top_level.txt
