Metadata-Version: 2.0
Name: django-aggregates
Version: 0.1.3
Summary: Aggregate, String and Conditional SQL functions for Django ORM.
Home-page: https://github.com/aykut/django-aggregates
Author: Aykut Ozat
Author-email: aykutozat@gmail.com
License: UNKNOWN
Platform: UNKNOWN
Classifier: Environment :: Web Environment
Classifier: Framework :: Django
Classifier: Intended Audience :: Developers
Classifier: License :: OSI Approved :: BSD License
Classifier: Operating System :: OS Independent
Classifier: Programming Language :: Python
Classifier: Topic :: Internet :: WWW/HTTP
Classifier: Topic :: Internet :: WWW/HTTP :: Dynamic Content
Requires-Dist: django (>=1.2)
